tex_minify/__init__.py
tex_minify/bib_processor.py
tex_minify/cli.py
tex_minify/processor.py
tex_minify-0.2.6.dist-info/METADATA
tex_minify-0.2.6.dist-info/WHEEL
tex_minify-0.2.6.dist-info/entry_points.txt
tex_minify-0.2.6.dist-info/RECORD
