Metadata-Version: 2.4
Name: tex-minify
Version: 0.2.6
Summary: A CLI tool to expand \input commands in TeX files and filter BibTeX files based on citations.
Project-URL: Homepage, https://github.com/yourusername/tex-minify
Project-URL: Repository, https://github.com/yourusername/tex-minify.git
Project-URL: Bug Tracker, https://github.com/yourusername/tex-minify/issues
Author-email: Dariush Wahdany <dariushwahdany@gmail.com>
License: MIT
Keywords: cli,latex,preprocessor,tex
Classifier: Development Status :: 4 - Beta
Classifier: Environment :: Console
Classifier: Intended Audience :: Science/Research
Classifier: License :: OSI Approved :: MIT License
Classifier: Programming Language :: Python :: 3.11
Classifier: Topic :: Text Processing :: Markup :: LaTeX
Requires-Python: >=3.11
Requires-Dist: click>=8.1.0
